graph_garden/__init__.py
graph_garden/arangodb.py
graph_garden/cli.py
graph_garden-0.1.2.dist-info/entry_points.txt
graph_garden-0.1.2.dist-info/LICENSE
graph_garden-0.1.2.dist-info/WHEEL
graph_garden-0.1.2.dist-info/METADATA
graph_garden-0.1.2.dist-info/RECORD
